snowenv/__init__.py
snowenv/_version.py
snowenv/connector.py
snowenv/generate.py
snowenv/utils.py
snowenv-0.1.0.dist-info/LICENSE
snowenv-0.1.0.dist-info/METADATA
snowenv-0.1.0.dist-info/WHEEL
snowenv-0.1.0.dist-info/top_level.txt
snowenv-0.1.0.dist-info/RECORD
