Metadata-Version: 2.1
Name: snowenv
Version: 0.1.0
Summary: Environment switching for Snowflake Connector for Python
Home-page: https://github.com/gouline/snowenv-python
Author: Mike Gouline
Author-email: hello@gouline.net
License: Apache License 2.0
Platform: UNKNOWN
Classifier: Development Status :: 3 - Alpha
Classifier: Intended Audience :: Developers
Classifier: License :: OSI Approved :: Apache Software License
Classifier: Operating System :: OS Independent
Classifier: Programming Language :: Python
Classifier: Programming Language :: Python :: 3 :: Only
Classifier: Programming Language :: Python :: 3.6
Classifier: Programming Language :: Python :: 3.7
Classifier: Programming Language :: Python :: 3.8
Classifier: Programming Language :: Python :: 3.9
Classifier: Topic :: Software Development :: Libraries
Classifier: Topic :: Software Development :: Libraries :: Python Modules
Requires-Dist: Jinja2
Requires-Dist: PyYAML
Requires-Dist: python-dotenv
Requires-Dist: ruamel.yaml
Requires-Dist: snowflake-connector-python
Provides-Extra: test
Requires-Dist: black ; extra == 'test'
Requires-Dist: mypy ; extra == 'test'
Requires-Dist: pylint ; extra == 'test'
